dailylogfile/__init__.py
dailylogfile/dailylogging.py
dailylogfile-0.3.1.dist-info/licenses/LICENSE
dailylogfile-0.3.1.dist-info/METADATA
dailylogfile-0.3.1.dist-info/WHEEL
dailylogfile-0.3.1.dist-info/top_level.txt
dailylogfile-0.3.1.dist-info/RECORD
