Metadata-Version: 2.4
Name: dailylogfile
Version: 0.3.1
Summary: Opinionated daily log file manager with date formatting and compression.
Author: James Reed
Maintainer: James Reed
License-Expression: MIT
Project-URL: Homepage, https://github.com/jamespreed/dailylogfile
Project-URL: Issues, https://github.com/jamespreed/dailylogfile/issues
Classifier: Development Status :: 4 - Beta
Classifier: Intended Audience :: Developers
Classifier: Programming Language :: Python
Classifier: Programming Language :: Python :: 3 :: Only
Requires-Python: >=3.9
License-File: LICENSE
Provides-Extra: test
Requires-Dist: pytest>=6.0; extra == "test"
Requires-Dist: freezegun>=1.2; extra == "test"
Requires-Dist: coverage; extra == "test"
Requires-Dist: pytest-cov; extra == "test"
Dynamic: license-file
